psdls/app.py
psdls/buildtools.py
psdls/clock.py
psdls/logger.py
psdls/resource.py
psdls/window.py
pysdlstrap-0.1.0.dist-info/METADATA
pysdlstrap-0.1.0.dist-info/WHEEL
pysdlstrap-0.1.0.dist-info/top_level.txt
pysdlstrap-0.1.0.dist-info/RECORD
