Metadata-Version: 2.1
Name: pysdlstrap
Version: 0.1.0
Summary: PySDLStrap - is a wrapper for SDL2 library for writting optimized apps in python on high-level language.
Home-page: https://github.com/nesquikcode/pysdlstrap
Author: nesquik
Author-email: nesquik@nishine.ru
License: MIT
Keywords: app apps pygame sdl sdl2 wrapper python bootstrap framework game engine
Requires-Dist: PySDL2==0.9.16
Requires-Dist: pysdl2-dll>=2.30.9
